agentos/__init__.py
agentos/cli.py
agentos/settings.py
agentos/types.py
agentos/core/__init__.py
agentos/core/config.py
agentos/core/installer.py
agentos/core/shell.py
agentos/utils/__init__.py
agentos/utils/validation.py
agent_os_cli-1.5.0.dist-info/METADATA
agent_os_cli-1.5.0.dist-info/WHEEL
agent_os_cli-1.5.0.dist-info/entry_points.txt
agent_os_cli-1.5.0.dist-info/licenses/LICENSE
agent_os_cli-1.5.0.dist-info/RECORD
